boolify/__init__.py
boolify/__version__.py
boolify-0.0.4.dev0.dist-info/LICENSE
boolify-0.0.4.dev0.dist-info/METADATA
boolify-0.0.4.dev0.dist-info/WHEEL
boolify-0.0.4.dev0.dist-info/top_level.txt
boolify-0.0.4.dev0.dist-info/RECORD
