Metadata-Version: 2.1
Name: boolify
Version: 0.0.4.dev0
Summary: Convert common strings into bool values.
Home-page: https://github.com/luissilva1044894/boolify
Author: Luis (Lugg) Gustavo
Author-email: the.nonsocial@gmail.com
Maintainer: Luis (Lugg) Gustavo
Maintainer-email: the.nonsocial@gmail.com
License: MIT
Download-URL: https://github.com/luissilva1044894/boolify/archive/0.0.4.dev0.tar.gz
Project-URL: Discord: Support Server, https://discord.gg/XkydRPS
Project-URL: Github: Issues, https://github.com/luissilva1044894/boolify/issues
Project-URL: Say Thanks!, https://saythanks.io/to/luissilva1044894
Keywords: boolify,bool,boolean,convert,open-source,library,python,python3,python-3
Platform: any
Classifier: Development Status :: 4 - Beta
Classifier: Intended Audience :: Developers
Classifier: License :: OSI Approved :: MIT License
Classifier: Natural Language :: English
Classifier: Operating System :: OS Independent
Classifier: Programming Language :: Python
Classifier: Programming Language :: Python :: 3
Classifier: Programming Language :: Python :: 3.6
Classifier: Programming Language :: Python :: 3.7
Classifier: Programming Language :: Python :: 3.8
Classifier: Programming Language :: Python :: Implementation :: CPython
Classifier: Topic :: Software Development
Classifier: Topic :: Software Development :: Libraries
Classifier: Topic :: Software Development :: Libraries :: Python Modules
Classifier: Topic :: Utilities
Requires-Python: >=3.6.*
Requires-Dist: colorama ; os_name == "nt"
Provides-Extra: dev
Requires-Dist: packaging (~=19.2) ; extra == 'dev'
Requires-Dist: pip (~=19.3.1) ; extra == 'dev'
Requires-Dist: pipenv (~=2018.11.26) ; extra == 'dev'
Requires-Dist: setuptools (~=42.0.2) ; extra == 'dev'
Requires-Dist: twine (~=3.1.1) ; extra == 'dev'
Requires-Dist: virtualenv (~=16.7.8) ; extra == 'dev'
Requires-Dist: wheel (~=0.33.6) ; extra == 'dev'
Requires-Dist: pytest (~=5.3.1) ; extra == 'dev'
Requires-Dist: colorama ; (os_name == "nt") and extra == 'dev'
Requires-Dist: sphinx-rtd-theme (~=0.4.3) ; (sys_platform == "win32") and extra == 'dev'
Provides-Extra: docs
Requires-Dist: colorama ; (os_name == "nt") and extra == 'docs'
Requires-Dist: sphinx-rtd-theme (~=0.4.3) ; (sys_platform == "win32") and extra == 'docs'
